lynx_logger/__init__.py
lynx_logger/config.py
lynx_logger/context.py
lynx_logger/core.py
lynx_logger/filters.py
lynx_logger/formatters.py
lynx_logger/middleware.py
lynx_logger-1.0.1.dist-info/licenses/LICENSE
tests/__init__.py
tests/conftest.py
tests/test_config.py
tests/test_context.py
tests/test_core.py
tests/test_formatters.py
tests/test_integration.py
tests/test_setup_logger.py
lynx_logger-1.0.1.dist-info/METADATA
lynx_logger-1.0.1.dist-info/WHEEL
lynx_logger-1.0.1.dist-info/top_level.txt
lynx_logger-1.0.1.dist-info/RECORD
